setup.py
django_cape/__init__.py
django_cape/models.py
django_cape.egg-info/PKG-INFO
django_cape.egg-info/SOURCES.txt
django_cape.egg-info/dependency_links.txt
django_cape.egg-info/requires.txt
django_cape.egg-info/top_level.txt
django_cape/templates/cape/base.html
django_cape/templates/cape/shell.html