Metadata-Version: 1.0
Name: django-cape
Version: 0.2
Summary: Django app that provides CAPE templates for progressive enhancement.
Home-page: https://github.com/devfort/django-cape
Author: James Aylett and Mark Norman Francis
Author-email: contact@devfort.com
License: MIT
Platform: UNKNOWN
Classifier: Intended Audience :: Developers
Classifier: Framework :: Django
Classifier: License :: OSI Approved :: MIT License
Classifier: Programming Language :: Python :: 2
Classifier: Programming Language :: Python :: 3
